kingman
